yadage/__init__.py
yadage/clihelpers.py
yadage/controllers.py
yadage/helpers.py
yadage/interactive.py
yadage/manualcli.py
yadage/manualutils.py
yadage/reset.py
yadage/serialize.py
yadage/stages.py
yadage/steering.py
yadage/steering_api.py
yadage/steering_object.py
yadage/utilcli.py
yadage/validator_workflow.py
yadage/visualize.py
yadage/wflow.py
yadage/wflownode.py
yadage/wflowview.py
yadage/workflow_loader.py
yadage/yadagestep.py
yadage/backends/__init__.py
yadage/backends/caching.py
yadage/backends/federatedbackend.py
yadage/backends/packtivitybackend.py
yadage/backends/trivialbackend.py
yadage/handlers/__init__.py
yadage/handlers/expression_handlers.py
yadage/handlers/predicate_handlers.py
yadage/handlers/scheduler_handlers.py
yadage/handlers/utils.py
yadage_fork-0.11.0.dist-info/DESCRIPTION.rst
yadage_fork-0.11.0.dist-info/METADATA
yadage_fork-0.11.0.dist-info/RECORD
yadage_fork-0.11.0.dist-info/WHEEL
yadage_fork-0.11.0.dist-info/entry_points.txt
yadage_fork-0.11.0.dist-info/metadata.json
yadage_fork-0.11.0.dist-info/top_level.txt
